flake8_variables_names/__init__.py
flake8_variables_names/ast_helpers.py
flake8_variables_names/checker.py
flake8_variables_names/list_helpers.py
flake8_variables_names-0.0.6.dist-info/LICENSE
flake8_variables_names-0.0.6.dist-info/METADATA
flake8_variables_names-0.0.6.dist-info/WHEEL
flake8_variables_names-0.0.6.dist-info/entry_points.txt
flake8_variables_names-0.0.6.dist-info/top_level.txt
flake8_variables_names-0.0.6.dist-info/RECORD
