Metadata-Version: 2.1
Name: flake8_variables_names
Version: 0.0.6
Summary: A flake8 extension that helps to make more readable variables names
Home-page: https://github.com/best-doctor/flake8-variables-names
Author: Ilya Lebedev
Author-email: melevir@gmail.com
License: MIT
Keywords: flake8 naming
Classifier: Environment :: Console
Classifier: Operating System :: OS Independent
Classifier: Topic :: Software Development :: Documentation
Classifier: Topic :: Software Development :: Libraries :: Python Modules
Classifier: Topic :: Software Development :: Quality Assurance
Classifier: Programming Language :: Python
Classifier: Programming Language :: Python :: 3.7
Classifier: Programming Language :: Python :: 3.8
Classifier: Programming Language :: Python :: 3.9
Classifier: Programming Language :: Python :: 3.10
Requires-Python: >=3.7
License-File: LICENSE
